{"isAutoGenerated":true,"pitfallCountValue":1,"stateCount":10,"agentsCount":50,"states":[{"id":0,"targetIds":[1],"agents":[{"id":13,"targetStateId":8,"capacity":{"trustHistoryItemCap":15,"trustHistoryCap":20,"watchListCapacity":18,"watchDepth":1,"travelHistoryCap":118,"capPower":67}},{"id":36,"targetStateId":2,"capacity":{"trustHistoryItemCap":15,"trustHistoryCap":87,"watchListCapacity":9,"watchDepth":1,"travelHistoryCap":83,"capPower":53}}],"capacity":47,"isPitfall":false},{"id":1,"targetIds":[9],"agents":[{"id":4,"targetStateId":2,"capacity":{"trustHistoryItemCap":15,"trustHistoryCap":73,"watchListCapacity":22,"watchDepth":0,"travelHistoryCap":116,"capPower":46}},{"id":9,"targetStateId":0,"capacity":{"trustHistoryItemCap":15,"trustHistoryCap":24,"watchListCapacity":38,"watchDepth":0,"travelHistoryCap":48,"capPower":19}},{"id":18,"targetStateId":1,"capacity":{"trustHistoryItemCap":15,"trustHistoryCap":42,"watchListCapacity":21,"watchDepth":0,"travelHistoryCap":69,"capPower":27}},{"id":31,"targetStateId":4,"capacity":{"trustHistoryItemCap":15,"trustHistoryCap":42,"watchListCapacity":13,"watchDepth":0,"travelHistoryCap":28,"capPower":11}},{"id":35,"targetStateId":1,"capacity":{"trustHistoryItemCap":15,"trustHistoryCap":10,"watchListCapacity":8,"watchDepth":0,"travelHistoryCap":85,"capPower":34}},{"id":44,"targetStateId":2,"capacity":{"trustHistoryItemCap":15,"trustHistoryCap":54,"watchListCapacity":28,"watchDepth":1,"travelHistoryCap":53,"capPower":41}}],"capacity":50,"isPitfall":false},{"id":2,"targetIds":[7,0],"agents":[{"id":16,"targetStateId":9,"capacity":{"trustHistoryItemCap":15,"trustHistoryCap":77,"watchListCapacity":20,"watchDepth":0,"travelHistoryCap":141,"capPower":56}},{"id":17,"targetStateId":5,"capacity":{"trustHistoryItemCap":15,"trustHistoryCap":44,"watchListCapacity":4,"watchDepth":1,"travelHistoryCap":88,"capPower":55}},{"id":19,"targetStateId":0,"capacity":{"trustHistoryItemCap":15,"trustHistoryCap":93,"watchListCapacity":13,"watchDepth":0,"travelHistoryCap":77,"capPower":30}},{"id":30,"targetStateId":0,"capacity":{"trustHistoryItemCap":15,"trustHistoryCap":37,"watchListCapacity":14,"watchDepth":0,"travelHistoryCap":17,"capPower":6}},{"id":41,"targetStateId":3,"capacity":{"trustHistoryItemCap":15,"trustHistoryCap":81,"watchListCapacity":26,"watchDepth":1,"travelHistoryCap":140,"capPower":76}},{"id":48,"targetStateId":3,"capacity":{"trustHistoryItemCap":15,"trustHistoryCap":89,"watchListCapacity":13,"watchDepth":0,"travelHistoryCap":15,"capPower":6}}],"capacity":45,"isPitfall":false},{"id":3,"targetIds":[1,5,0],"agents":[{"id":23,"targetStateId":1,"capacity":{"trustHistoryItemCap":15,"trustHistoryCap":38,"watchListCapacity":5,"watchDepth":0,"travelHistoryCap":11,"capPower":4}},{"id":34,"targetStateId":0,"capacity":{"trustHistoryItemCap":15,"trustHistoryCap":85,"watchListCapacity":12,"watchDepth":1,"travelHistoryCap":17,"capPower":26}},{"id":46,"targetStateId":7,"capacity":{"trustHistoryItemCap":15,"trustHistoryCap":48,"watchListCapacity":30,"watchDepth":0,"travelHistoryCap":132,"capPower":52}},{"id":50,"targetStateId":1,"capacity":{"trustHistoryItemCap":15,"trustHistoryCap":60,"watchListCapacity":18,"watchDepth":0,"travelHistoryCap":110,"capPower":44}}],"capacity":78,"isPitfall":false},{"id":4,"targetIds":[2,7,8],"agents":[{"id":1,"targetStateId":9,"capacity":{"trustHistoryItemCap":15,"trustHistoryCap":93,"watchListCapacity":12,"watchDepth":1,"travelHistoryCap":53,"capPower":41}},{"id":7,"targetStateId":4,"capacity":{"trustHistoryItemCap":15,"trustHistoryCap":65,"watchListCapacity":25,"watchDepth":1,"travelHistoryCap":109,"capPower":63}},{"id":10,"targetStateId":7,"capacity":{"trustHistoryItemCap":15,"trustHistoryCap":27,"watchListCapacity":1,"watchDepth":0,"travelHistoryCap":29,"capPower":11}},{"id":45,"targetStateId":1,"capacity":{"trustHistoryItemCap":15,"trustHistoryCap":17,"watchListCapacity":28,"watchDepth":0,"travelHistoryCap":123,"capPower":49}},{"id":49,"targetStateId":3,"capacity":{"trustHistoryItemCap":15,"trustHistoryCap":57,"watchListCapacity":7,"watchDepth":0,"travelHistoryCap":28,"capPower":11}}],"capacity":60,"isPitfall":false},{"id":5,"targetIds":[4],"agents":[{"id":2,"targetStateId":7,"capacity":{"trustHistoryItemCap":15,"trustHistoryCap":92,"watchListCapacity":27,"watchDepth":1,"travelHistoryCap":47,"capPower":38}},{"id":5,"targetStateId":1,"capacity":{"trustHistoryItemCap":15,"trustHistoryCap":81,"watchListCapacity":18,"watchDepth":1,"travelHistoryCap":81,"capPower":52}},{"id":6,"targetStateId":0,"capacity":{"trustHistoryItemCap":15,"trustHistoryCap":86,"watchListCapacity":4,"watchDepth":1,"travelHistoryCap":94,"capPower":57}},{"id":11,"targetStateId":9,"capacity":{"trustHistoryItemCap":15,"trustHistoryCap":76,"watchListCapacity":7,"watchDepth":0,"travelHistoryCap":76,"capPower":30}},{"id":12,"targetStateId":1,"capacity":{"trustHistoryItemCap":15,"trustHistoryCap":49,"watchListCapacity":2,"watchDepth":1,"travelHistoryCap":116,"capPower":66}},{"id":20,"targetStateId":2,"capacity":{"trustHistoryItemCap":15,"trustHistoryCap":50,"watchListCapacity":9,"watchDepth":0,"travelHistoryCap":67,"capPower":26}},{"id":21,"targetStateId":1,"capacity":{"trustHistoryItemCap":15,"trustHistoryCap":79,"watchListCapacity":10,"watchDepth":0,"travelHistoryCap":77,"capPower":30}},{"id":22,"targetStateId":0,"capacity":{"trustHistoryItemCap":15,"trustHistoryCap":46,"watchListCapacity":22,"watchDepth":0,"travelHistoryCap":110,"capPower":44}},{"id":26,"targetStateId":4,"capacity":{"trustHistoryItemCap":15,"trustHistoryCap":65,"watchListCapacity":10,"watchDepth":1,"travelHistoryCap":14,"capPower":25}},{"id":39,"targetStateId":2,"capacity":{"trustHistoryItemCap":15,"trustHistoryCap":15,"watchListCapacity":31,"watchDepth":1,"travelHistoryCap":92,"capPower":56}},{"id":47,"targetStateId":4,"capacity":{"trustHistoryItemCap":15,"trustHistoryCap":94,"watchListCapacity":16,"watchDepth":0,"travelHistoryCap":57,"capPower":22}}],"capacity":45,"isPitfall":false},{"id":6,"targetIds":[],"agents":[],"capacity":65,"isPitfall":true},{"id":7,"targetIds":[9],"agents":[{"id":3,"targetStateId":2,"capacity":{"trustHistoryItemCap":15,"trustHistoryCap":84,"watchListCapacity":31,"watchDepth":1,"travelHistoryCap":62,"capPower":44}},{"id":14,"targetStateId":2,"capacity":{"trustHistoryItemCap":15,"trustHistoryCap":25,"watchListCapacity":13,"watchDepth":0,"travelHistoryCap":99,"capPower":39}},{"id":24,"targetStateId":5,"capacity":{"trustHistoryItemCap":15,"trustHistoryCap":44,"watchListCapacity":31,"watchDepth":0,"travelHistoryCap":127,"capPower":50}},{"id":27,"targetStateId":7,"capacity":{"trustHistoryItemCap":15,"trustHistoryCap":24,"watchListCapacity":24,"watchDepth":1,"travelHistoryCap":84,"capPower":53}},{"id":29,"targetStateId":4,"capacity":{"trustHistoryItemCap":15,"trustHistoryCap":92,"watchListCapacity":16,"watchDepth":1,"travelHistoryCap":64,"capPower":45}},{"id":38,"targetStateId":3,"capacity":{"trustHistoryItemCap":15,"trustHistoryCap":12,"watchListCapacity":15,"watchDepth":0,"travelHistoryCap":118,"capPower":47}},{"id":40,"targetStateId":3,"capacity":{"trustHistoryItemCap":15,"trustHistoryCap":57,"watchListCapacity":11,"watchDepth":1,"travelHistoryCap":135,"capPower":74}},{"id":42,"targetStateId":3,"capacity":{"trustHistoryItemCap":15,"trustHistoryCap":38,"watchListCapacity":0,"watchDepth":1,"travelHistoryCap":115,"capPower":66}}],"capacity":70,"isPitfall":false},{"id":8,"targetIds":[1],"agents":[{"id":8,"targetStateId":3,"capacity":{"trustHistoryItemCap":15,"trustHistoryCap":29,"watchListCapacity":0,"watchDepth":0,"travelHistoryCap":110,"capPower":44}},{"id":25,"targetStateId":7,"capacity":{"trustHistoryItemCap":15,"trustHistoryCap":39,"watchListCapacity":5,"watchDepth":0,"travelHistoryCap":122,"capPower":48}},{"id":28,"targetStateId":8,"capacity":{"trustHistoryItemCap":15,"trustHistoryCap":32,"watchListCapacity":13,"watchDepth":1,"travelHistoryCap":22,"capPower":28}},{"id":37,"targetStateId":5,"capacity":{"trustHistoryItemCap":15,"trustHistoryCap":72,"watchListCapacity":3,"watchDepth":0,"travelHistoryCap":60,"capPower":24}},{"id":43,"targetStateId":1,"capacity":{"trustHistoryItemCap":15,"trustHistoryCap":28,"watchListCapacity":7,"watchDepth":0,"travelHistoryCap":36,"capPower":14}}],"capacity":43,"isPitfall":false},{"id":9,"targetIds":[3,4],"agents":[{"id":15,"targetStateId":8,"capacity":{"trustHistoryItemCap":15,"trustHistoryCap":89,"watchListCapacity":16,"watchDepth":0,"travelHistoryCap":87,"capPower":34}},{"id":32,"targetStateId":7,"capacity":{"trustHistoryItemCap":15,"trustHistoryCap":48,"watchListCapacity":30,"watchDepth":1,"travelHistoryCap":30,"capPower":32}},{"id":33,"targetStateId":5,"capacity":{"trustHistoryItemCap":15,"trustHistoryCap":39,"watchListCapacity":12,"watchDepth":0,"travelHistoryCap":59,"capPower":23}}],"capacity":62,"isPitfall":false}]}